data_fabric/__init__.py
test_data_fabric-0.0.1.dist-info/LICENSE
test_data_fabric-0.0.1.dist-info/METADATA
test_data_fabric-0.0.1.dist-info/WHEEL
test_data_fabric-0.0.1.dist-info/top_level.txt
test_data_fabric-0.0.1.dist-info/RECORD
