Metadata-Version: 2.1
Name: test-data-fabric
Version: 0.0.1
Summary: UNKNOWN
Home-page: UNKNOWN
Author: Bluepinapple
Author-email: viveksthul@bluepinapple.com
License: UNKNOWN
Platform: UNKNOWN
Requires-Python: >=3.9.6
License-File: LICENSE
Requires-Dist: streamlit (>=1.20.0)
